[{
    
    "id": 1,
    "title": "Training Hundreds of Interior Designers to master 3dsmax & Vray for more than 15 Years  !! ",
    "subTitle": "Get a 50 % Discount on the Best V-RAY LIVE Online Training",
    "image": "/images/misc/interiorVray.jpg",

    "alt": " ",
    "direction": "row"
       
    },
   

    {
    
        "id": 5,
        "title": "Get A FREE Autocad Online-Live Course! ",
        "subTitle": "Offer is Exclusive For 3dsmax Registered Students",
        "image": "/images/misc/3dsmax.jpg",
        "alt": "",
        "direction": "row"
    },



    {
    
        "id": 2,
        "title": "Learn How To Finish this 3dsmax scene in 15 mins !!",
        "subTitle": "Learn how to Use 3dsmax As Easy as Sketchup!!",
        "image": "/images/misc/3D Dilemma 01.jpg",
        "alt": "",
        "direction": "row"
    }
 
    ,
    {
    
        "id": 3,
        "title": "In The Modeling Part OF The Course Master The 3D Art OF Furniture Modeling!",
    "subTitle": "3dsmax Is The Number 1 Tool For Interior Designers!",
        "image": "/images/misc/3D Dilemma 03.jpg",
        "alt": "",
        "direction": "row"
    }
    ,
    {
    
        "id": 4,
        "title": "Get FREE Online Project Support For 1 Year After The Course!!",
        "subTitle": "We Are The Only Training Provider that Supports 3D Projects for Students !! ",
        "image": "/images/misc/3D Dilemma 04.jpg",
        "alt": "",
        "direction": "row"
    }
    ,
   
     {
    
        "id": 7,
        "title": "UnrealEngine Real-time Render Courses For Architects & Interior Designers!!",
        "subTitle": "Coming Soon!!",
        "image": "/images/misc/RT.jpg",
        "alt": "",
        "direction": "row"
    }
    ,
    
    {
    
        "id": 6,
        "title": "The First Digital Avatar for education HalaBot3D!!",
        "subTitle": "Coming Soon!!",
        "image": "/images/misc/HalaBot3D.jpg",
        "alt": "",
        "direction": "row"
    }
]